ta_x/__init__.py
ta_x/agent.py
ta_x/base.py
ta_x/cli.py
ta_x/config.py
ta_x/endpoints.py
ta_x/schema.py
ta_x/tools.py
ta_x_agent-0.1.2.dist-info/METADATA
ta_x_agent-0.1.2.dist-info/WHEEL
ta_x_agent-0.1.2.dist-info/entry_points.txt
ta_x_agent-0.1.2.dist-info/top_level.txt
ta_x_agent-0.1.2.dist-info/RECORD
