Metadata-Version: 2.4
Name: ta-x-agent
Version: 0.1.2
Summary: A Python package for interacting with X (Twitter) platform using AI agents
Home-page: https://github.com/Soumyajit22theagentic/ta_x
Author: Soumyajit
Author-email: Soumyajit <soumyajit@theagentic.ai>
Maintainer-email: Soumyajit <soumyajit@theagentic.ai>
License: MIT
Project-URL: Homepage, https://github.com/Soumyajit22theagentic/ta_x
Project-URL: Documentation, https://github.com/Soumyajit22theagentic/ta_x#readme
Project-URL: Repository, https://github.com/Soumyajit22theagentic/ta_x
Project-URL: Bug Tracker, https://github.com/Soumyajit22theagentic/ta_x/issues
Keywords: twitter,x,social media,ai,agent,automation
Classifier: Development Status :: 3 - Alpha
Classifier: Intended Audience :: Developers
Classifier: License :: OSI Approved :: MIT License
Classifier: Operating System :: OS Independent
Classifier: Programming Language :: Python :: 3
Classifier: Programming Language :: Python :: 3.8
Classifier: Programming Language :: Python :: 3.9
Classifier: Programming Language :: Python :: 3.10
Classifier: Programming Language :: Python :: 3.11
Classifier: Programming Language :: Python :: 3.12
Classifier: Topic :: Internet :: WWW/HTTP
Classifier: Topic :: Software Development :: Libraries :: Python Modules
Requires-Python: >=3.8
Requires-Dist: pydantic>=2.0.0
Requires-Dist: pydantic-ai>=0.1.0
Requires-Dist: requests>=2.25.0
Requires-Dist: python-dotenv>=0.19.0
Requires-Dist: logfire>=0.1.0
Provides-Extra: dev
Requires-Dist: pytest>=6.0; extra == "dev"
Requires-Dist: pytest-asyncio>=0.18.0; extra == "dev"
Requires-Dist: black>=21.0; extra == "dev"
Requires-Dist: flake8>=3.8; extra == "dev"
Requires-Dist: mypy>=0.800; extra == "dev"
Dynamic: author
Dynamic: home-page
Dynamic: requires-python
